{
    "metadata":  {
                     "generatedAt":  "2026-03-25 20:28:15 -06:00",
                     "status":  "generated"
                 },
    "resorts":  {
                    "alta":  {
                                 "sourceUpdatedAt":  " ",
                                 "sourceNotes":  "Live refresh pipeline fetched the official resort page on 2026-03-25 20:28:15 -06:00.",
                                 "officialStats":  {

                                                   }
                             },
                    "big-sky":  {
                                    "sourceUpdatedAt":  "Fetched 2026-03-25 20:28:15 -06:00; resort timestamp unavailable",
                                    "sourceNotes":  "Live refresh pipeline fetched the official resort page on 2026-03-25 20:28:15 -06:00.",
                                    "officialStats":  {
                                                          "snowfall24Hours":  72,
                                                          "baseDepthMin":  40,
                                                          "baseDepthMax":  40,
                                                          "trailsOpen":  95,
                                                          "trailsTotal":  320,
                                                          "liftsOpen":  27,
                                                          "liftsTotal":  5
                                                      }
                                },
                    "snowbasin":  {
                                      "sourceUpdatedAt":  "Mar 21 5:53 AM MT",
                                      "sourceNotes":  "Live refresh pipeline fetched the official resort page on 2026-03-25 20:28:15 -06:00.",
                                      "officialStats":  {

                                                        }
                                  },
                    "snowbird":  {
                                     "sourceUpdatedAt":  " ",
                                     "sourceNotes":  "Live refresh pipeline fetched the official resort page on 2026-03-25 20:28:15 -06:00.",
                                     "officialStats":  {

                                                       }
                                 },
                    "grand-targhee":  {
                                          "sourceUpdatedAt":  "7:00am",
                                          "sourceNotes":  "Live refresh pipeline fetched the official resort page on 2026-03-25 20:28:15 -06:00.",
                                          "officialStats":  {

                                                            }
                                      },
                    "sun-valley":  {
                                       "sourceUpdatedAt":  "Mar 25, 5:20 AM MT",
                                       "sourceNotes":  "Live refresh pipeline fetched the official resort page on 2026-03-25 20:28:15 -06:00.",
                                       "officialStats":  {

                                                         }
                                   },
                    "sugarloaf":  {
                                      "sourceUpdatedAt":  "Fetched 2026-03-25 20:28:15 -06:00; resort timestamp unavailable",
                                      "sourceNotes":  "Live refresh pipeline fetched the official resort page on 2026-03-25 20:28:15 -06:00.",
                                      "officialStats":  {

                                                        }
                                  },
                    "sunday-river":  {
                                         "sourceUpdatedAt":  "Fetched 2026-03-25 20:28:15 -06:00; resort timestamp unavailable",
                                         "sourceNotes":  "Live refresh pipeline fetched the official resort page on 2026-03-25 20:28:15 -06:00.",
                                         "officialStats":  {

                                                           }
                                     },
                    "taos":  {
                                 "sourceUpdatedAt":  "Fetched 2026-03-25 20:28:15 -06:00; resort timestamp unavailable",
                                 "sourceNotes":  "Live refresh pipeline fetched the official resort page on 2026-03-25 20:28:15 -06:00.",
                                 "officialStats":  {

                                                   }
                             },
                    "jackson-hole":  {
                                         "sourceUpdatedAt":  "Fetched 2026-03-25 20:28:15 -06:00; resort timestamp unavailable",
                                         "sourceNotes":  "Live refresh pipeline fetched the official resort page on 2026-03-25 20:28:15 -06:00.",
                                         "officialStats":  {

                                                           }
                                     }
                }
}
